sphinx_ncs_theme/__init__.py
sphinx_ncs_theme/breadcrumbs.html
sphinx_ncs_theme/footer.html
sphinx_ncs_theme/layout.html
sphinx_ncs_theme/search.html
sphinx_ncs_theme/searchbox.html
sphinx_ncs_theme/theme.conf
sphinx_ncs_theme/versions.html
sphinx_ncs_theme/static/css/bootstrap.min.css
sphinx_ncs_theme/static/css/nordic.css
sphinx_ncs_theme/static/images/dropdown.svg
sphinx_ncs_theme/static/images/favicon.ico
sphinx_ncs_theme/static/images/header-bg.svg
sphinx_ncs_theme/static/images/nordic-logo.png
sphinx_ncs_theme/static/images/search.svg
sphinx_ncs_theme/static/js/bootstrap.bundle.min.js
sphinx_ncs_theme/static/js/ncs.js
sphinx_ncs_theme/static/js/theme.js
sphinx_ncs_theme-1.0.21.dist-info/METADATA
sphinx_ncs_theme-1.0.21.dist-info/WHEEL
sphinx_ncs_theme-1.0.21.dist-info/entry_points.txt
sphinx_ncs_theme-1.0.21.dist-info/top_level.txt
sphinx_ncs_theme-1.0.21.dist-info/RECORD
