Metadata-Version: 2.1
Name: sphinx-ncs-theme
Version: 1.0.21
Summary: Nordic Semiconductor NCS theme for Sphinx
Home-page: https://www.nordicsemi.no
Author: Nordic Semiconductor ASA
License: MIT
Classifier: Framework :: Sphinx
Classifier: Framework :: Sphinx :: Theme
Classifier: Development Status :: 5 - Production/Stable
Classifier: License :: OSI Approved :: MIT License
Classifier: Environment :: Console
Classifier: Environment :: Web Environment
Classifier: Intended Audience :: Developers
Classifier: Programming Language :: Python :: 3 :: Only
Classifier: Operating System :: OS Independent
Classifier: Topic :: Documentation
Classifier: Topic :: Software Development :: Documentation
Requires-Dist: sphinx_rtd_theme>=2.0
